[{"json_units":"kmh","targets":[{"angle":-2.61558,"distance":25.3287,"id":1294522,"speed":-0.55,"strength":9822760}],"timestamp":16534,"ui_units":"kmh"},{"json_units":"kmh","targets":[{"angle":-2.6131,"distance":25.2833,"id":1294522,"speed":-0.55,"strength":4233580}],"timestamp":16534,"ui_units":"kmh"},{"json_units":"kmh","targets":[{"angle":-2.49451,"distance":25.3535,"id":1294522,"speed":0.55,"strength":5864270}],"timestamp":16534,"ui_units":"kmh"},{"json_units":"kmh","targets":[{"angle":-2.49984,"distance":25.3483,"id":1294522,"speed":-0.55,"strength":9912740}],"timestamp":16534,"ui_units":"kmh"},{"json_units":"kmh","targets":[{"angle":-2.32584,"distance":25.5104,"id":1294522,"speed":-0.55,"strength":6369490}],"timestamp":16535,"ui_units":"kmh"},{"json_units":"kmh","targets":[{"angle":-2.34146,"distance":26.0998,"id":1294522,"speed":0.55,"strength":4017860}],"timestamp":16535,"ui_units":"kmh"},{"json_units":"kmh","targets":[{"angle":-1.90197,"distance":26.0888,"id":1294522,"speed":0.55,"strength":5483040}],"timestamp":16535,"ui_units":"kmh"},{"json_units":"kmh","targets":[{"angle":0.211848,"distance":27.082,"id":1294522,"speed":-3.66974,"strength":543380}],"timestamp":16535,"ui_units":"kmh"},{"json_units":"kmh","targets":[{"angle":0.369007,"distance":27.0611,"id":1294522,"speed":-0.55,"strength":3805880}],"timestamp":16536,"ui_units":"kmh"},{"json_units":"kmh","targets":[{"angle":0.445514,"distance":27.1256,"id":1294522,"speed":-0.55,"strength":3805880}],"timestamp":16536,"ui_units":"kmh"},{"json_units":"kmh","targets":[{"angle":0.31371,"distance":26.9789,"id":1294522,"speed":-0.55,"strength":20739000}],"timestamp":16536,"ui_units":"kmh"},{"json_units":"kmh","targets":[{"angle":0.440985,"distance":27.0814,"id":1294522,"speed":-0.55,"strength":20739000}],"timestamp":16536,"ui_units":"kmh"},{"json_units":"kmh","targets":[{"angle":0.256556,"distance":26.885,"id":1294522,"speed":0.55,"strength":10655000}],"timestamp":16537,"ui_units":"kmh"},{"json_units":"kmh","targets":[{"angle":0.277588,"distance":26.7201,"id":1294522,"speed":0.55,"strength":8487360}],"timestamp":16537,"ui_units":"kmh"},{"json_units":"kmh","targets":[{"angle":0.254665,"distance":26.7299,"id":1294522,"speed":-0.55,"strength":6274000}],"timestamp":16537,"ui_units":"kmh"},{"json_units":"kmh","targets":[{"angle":0.275586,"distance":26.68,"id":1294522,"speed":0.55,"strength":8213920}],"timestamp":16537,"ui_units":"kmh"},{"json_units":"kmh","targets":[{"angle":0.334432,"distance":26.7196,"id":1294522,"speed":1.06137,"strength":3528470}],"timestamp":16538,"ui_units":"kmh"},{"json_units":"kmh","targets":[{"angle":0.377546,"distance":26.7273,"id":1294522,"speed":-0.55,"strength":5480600}],"timestamp":16538,"ui_units":"kmh"},{"json_units":"kmh","targets":[{"angle":0.293923,"distance":26.7331,"id":1294522,"speed":0.55,"strength":8427830}],"timestamp":16538,"ui_units":"kmh"},{"json_units":"kmh","targets":[{"angle":0.138472,"distance":26.6893,"id":1294522,"speed":0.55,"strength":13557000}],"timestamp":16538,"ui_units":"kmh"},{"json_units":"kmh","targets":[{"angle":0.157536,"distance":26.7013,"id":1294522,"speed":0.55,"strength":13557000}],"timestamp":16539,"ui_units":"kmh"},{"json_units":"kmh","targets":[{"angle":0.0254753,"distance":26.5554,"id":1294522,"speed":-0.55,"strength":27622400}],"timestamp":16539,"ui_units":"kmh"},{"json_units":"kmh","targets":[{"angle":-0.165834,"distance":26.3565,"id":1294522,"speed":0.55,"strength":20807600}],"timestamp":16539,"ui_units":"kmh"},{"json_units":"kmh","targets":[{"angle":-0.359601,"distance":26.1818,"id":1294522,"speed":-0.55,"strength":13597300}],"timestamp":16539,"ui_units":"kmh"},{"json_units":"kmh","targets":[{"angle":-0.779241,"distance":25.9983,"id":1294522,"speed":-0.55,"strength":15170500}],"timestamp":16539,"ui_units":"kmh"},{"json_units":"kmh","targets":[{"angle":-0.901684,"distance":25.9224,"id":1294522,"speed":0.55,"strength":15966200}],"timestamp":16540,"ui_units":"kmh"},{"json_units":"kmh","targets":[{"angle":-0.9585939999999999,"distance":25.9011,"id":1294522,"speed":1.06137,"strength":12833800}],"timestamp":16540,"ui_units":"kmh"},{"json_units":"kmh","targets":[{"angle":-1.03944,"distance":25.9183,"id":1294522,"speed":-1.06137,"strength":9960690}],"timestamp":16540,"ui_units":"kmh"},{"json_units":"kmh","targets":[{"angle":-1.15539,"distance":25.8573,"id":1294522,"speed":0.55,"strength":13423700}],"timestamp":16540,"ui_units":"kmh"},{"json_units":"kmh","targets":[{"angle":-0.423764,"distance":25.8571,"id":1294522,"speed":-3.14549,"strength":6912320}],"timestamp":16541,"ui_units":"kmh"},{"json_units":"kmh","targets":[{"angle":-0.936369,"distance":25.7458,"id":1294522,"speed":-3.14549,"strength":4961890}],"timestamp":16541,"ui_units":"kmh"},{"json_units":"kmh","targets":[{"angle":-1.06461,"distance":25.6626,"id":1294522,"speed":-0.55,"strength":20257600}],"timestamp":16541,"ui_units":"kmh"},{"json_units":"kmh","targets":[{"angle":-1.15566,"distance":25.6277,"id":1294522,"speed":0.55,"strength":27416900}],"timestamp":16541,"ui_units":"kmh"},{"json_units":"kmh","targets":[{"angle":-1.29393,"distance":25.5698,"id":1294522,"speed":0.55,"strength":12932700}],"timestamp":16542,"ui_units":"kmh"},{"json_units":"kmh","targets":[{"angle":-1.22521,"distance":25.5459,"id":1294522,"speed":-0.55,"strength":6370510}],"timestamp":16542,"ui_units":"kmh"},{"json_units":"kmh","targets":[{"angle":-1.13054,"distance":25.7503,"id":1294522,"speed":0.55,"strength":4433010}],"timestamp":16542,"ui_units":"kmh"},{"json_units":"kmh","targets":[{"angle":-0.897129,"distance":25.7762,"id":1294522,"speed":1.06137,"strength":7128120}],"timestamp":16542,"ui_units":"kmh"},{"json_units":"kmh","targets":[{"angle":-0.839597,"distance":25.8198,"id":1294522,"speed":-0.55,"strength":6570660}],"timestamp":16543,"ui_units":"kmh"},{"json_units":"kmh","targets":[{"angle":-0.885646,"distance":25.7864,"id":1294522,"speed":0.55,"strength":7916440}],"timestamp":16543,"ui_units":"kmh"},{"json_units":"kmh","targets":[{"angle":-0.757281,"distance":25.7517,"id":1294522,"speed":0.55,"strength":3977380}],"timestamp":16543,"ui_units":"kmh"},{"json_units":"kmh","targets":[{"angle":-0.605424,"distance":25.7114,"id":1294522,"speed":-0.55,"strength":4744380}],"timestamp":16543,"ui_units":"kmh"},{"json_units":"kmh","targets":[{"angle":-0.58307,"distance":25.7102,"id":1294522,"speed":-0.55,"strength":5299260}],"timestamp":16544,"ui_units":"kmh"},{"json_units":"kmh","targets":[{"angle":-0.171427,"distance":25.808,"id":1294522,"speed":0.55,"strength":3452950}],"timestamp":16544,"ui_units":"kmh"},{"json_units":"kmh","targets":[{"angle":0.224781,"distance":26.3332,"id":1294522,"speed":0.55,"strength":4726170}],"timestamp":16544,"ui_units":"kmh"},{"json_units":"kmh","targets":[{"angle":0.815367,"distance":27.5394,"id":1294522,"speed":-0.55,"strength":16152300}],"timestamp":16544,"ui_units":"kmh"},{"json_units":"kmh","targets":[{"angle":1.38707,"distance":28.3112,"id":1294522,"speed":-0.55,"strength":6824780}],"timestamp":16545,"ui_units":"kmh"},{"json_units":"kmh","targets":[{"angle":1.43864,"distance":28.4343,"id":1294522,"speed":-3.14549,"strength":8691060}],"timestamp":16545,"ui_units":"kmh"},{"json_units":"kmh","targets":[{"angle":1.47597,"distance":28.542,"id":1294522,"speed":-3.14549,"strength":6751400}],"timestamp":16545,"ui_units":"kmh"},{"json_units":"kmh","targets":[{"angle":1.9415,"distance":28.7116,"id":1294522,"speed":-2.62124,"strength":3846410}],"timestamp":16545,"ui_units":"kmh"},{"json_units":"kmh","targets":[{"angle":2.32005,"distance":29.9147,"id":1294522,"speed":-3.14549,"strength":4017150}],"timestamp":16546,"ui_units":"kmh"},{"json_units":"kmh","targets":[{"angle":2.47818,"distance":29.8513,"id":1294522,"speed":-3.14549,"strength":5375260}],"timestamp":16546,"ui_units":"kmh"},{"json_units":"kmh","targets":[{"angle":3.07998,"distance":30.1602,"id":1294522,"speed":-0.55,"strength":12063800}],"timestamp":16546,"ui_units":"kmh"},{"json_units":"kmh","targets":[{"angle":3.32255,"distance":29.5971,"id":1294522,"speed":-0.55,"strength":10120200}],"timestamp":16546,"ui_units":"kmh"},{"json_units":"kmh","targets":[{"angle":3.45914,"distance":29.2874,"id":1294522,"speed":0.55,"strength":9981190}],"timestamp":16547,"ui_units":"kmh"},{"json_units":"kmh","targets":[{"angle":3.88135,"distance":29.148,"id":1294522,"speed":-1.06137,"strength":8453040}],"timestamp":16547,"ui_units":"kmh"},{"json_units":"kmh","targets":[{"angle":4.21246,"distance":28.6829,"id":1294522,"speed":-0.55,"strength":8452120}],"timestamp":16547,"ui_units":"kmh"},{"json_units":"kmh","targets":[{"angle":4.45301,"distance":28.4381,"id":1294522,"speed":0.55,"strength":8508060}],"timestamp":16547,"ui_units":"kmh"},{"json_units":"kmh","targets":[{"angle":4.64813,"distance":29.0823,"id":1294522,"speed":0.55,"strength":19177400}],"timestamp":16548,"ui_units":"kmh"},{"json_units":"kmh","targets":[{"angle":4.68444,"distance":28.9699,"id":1294522,"speed":-0.55,"strength":10038800}],"timestamp":16548,"ui_units":"kmh"},{"json_units":"kmh","targets":[{"angle":4.5044,"distance":29.3108,"id":1294522,"speed":0.55,"strength":6489220}],"timestamp":16548,"ui_units":"kmh"},{"json_units":"kmh","targets":[{"angle":4.31176,"distance":28.8028,"id":1294522,"speed":0.55,"strength":16912800}],"timestamp":16548,"ui_units":"kmh"},{"json_units":"kmh","targets":[{"angle":4.18538,"distance":28.5077,"id":1294522,"speed":-0.55,"strength":18234800}],"timestamp":16549,"ui_units":"kmh"},{"json_units":"kmh","targets":[{"angle":4.19498,"distance":29.4595,"id":1294522,"speed":-0.55,"strength":4489400}],"timestamp":16549,"ui_units":"kmh"},{"json_units":"kmh","targets":[{"angle":4.19114,"distance":29.1839,"id":1294522,"speed":0.55,"strength":17010600}],"timestamp":16549,"ui_units":"kmh"},{"json_units":"kmh","targets":[{"angle":4.05868,"distance":28.9085,"id":1294522,"speed":-1.06137,"strength":23733400}],"timestamp":16549,"ui_units":"kmh"},{"json_units":"kmh","targets":[{"angle":3.95064,"distance":29.1368,"id":1294522,"speed":-0.55,"strength":14469100}],"timestamp":16550,"ui_units":"kmh"},{"json_units":"kmh","targets":[{"angle":4.17645,"distance":28.8421,"id":1294522,"speed":0.55,"strength":16585400}],"timestamp":16550,"ui_units":"kmh"},{"json_units":"kmh","targets":[{"angle":3.50528,"distance":28.2537,"id":1294522,"speed":0.55,"strength":14986100}],"timestamp":16550,"ui_units":"kmh"},{"json_units":"kmh","targets":[{"angle":3.51385,"distance":28.231,"id":1294522,"speed":0.55,"strength":14986100}],"timestamp":16550,"ui_units":"kmh"},{"json_units":"kmh","targets":[{"angle":3.37842,"distance":27.7836,"id":1294522,"speed":-0.55,"strength":14713500}],"timestamp":16551,"ui_units":"kmh"},{"json_units":"kmh","targets":[{"angle":3.00952,"distance":27.5091,"id":1294522,"speed":0.55,"strength":23683300}],"timestamp":16551,"ui_units":"kmh"},{"json_units":"kmh","targets":[{"angle":3.02538,"distance":27.9245,"id":1294522,"speed":-0.55,"strength":13133000}],"timestamp":16551,"ui_units":"kmh"},{"json_units":"kmh","targets":[{"angle":1.83114,"distance":27.2983,"id":1294522,"speed":-0.55,"strength":24577500}],"timestamp":16551,"ui_units":"kmh"},{"json_units":"kmh","targets":[{"angle":1.74002,"distance":27.2341,"id":1294522,"speed":-0.55,"strength":24577500}],"timestamp":16552,"ui_units":"kmh"},{"json_units":"kmh","targets":[{"angle":2.08519,"distance":27.026,"id":1294522,"speed":0.55,"strength":13551200}],"timestamp":16552,"ui_units":"kmh"},{"json_units":"kmh","targets":[{"angle":2.41442,"distance":26.8972,"id":1294522,"speed":-0.55,"strength":13855800}],"timestamp":16552,"ui_units":"kmh"},{"json_units":"kmh","targets":[{"angle":5.04679,"distance":27.8337,"id":1294522,"speed":-0.55,"strength":2224320}],"timestamp":16552,"ui_units":"kmh"},{"json_units":"kmh","targets":[{"angle":5.17104,"distance":27.8259,"id":1294522,"speed":-0.55,"strength":2224320}],"timestamp":16553,"ui_units":"kmh"},{"json_units":"kmh","targets":[{"angle":5.29537,"distance":27.8182,"id":1294522,"speed":-0.55,"strength":2224320}],"timestamp":16553,"ui_units":"kmh"},{"json_units":"kmh","targets":[{"angle":5.54422,"distance":27.8032,"id":1294522,"speed":-0.55,"strength":2224320}],"timestamp":16553,"ui_units":"kmh"},{"json_units":"kmh","targets":[{"angle":3.88097,"distance":27.2824,"id":1294522,"speed":0.55,"strength":24811800}],"timestamp":16553,"ui_units":"kmh"},{"json_units":"kmh","targets":[{"angle":2.68753,"distance":26.811,"id":1294522,"speed":-0.55,"strength":17878200}],"timestamp":16554,"ui_units":"kmh"},{"json_units":"kmh","targets":[{"angle":2.0147,"distance":26.5272,"id":1294522,"speed":-0.55,"strength":17579700}],"timestamp":16554,"ui_units":"kmh"},{"json_units":"kmh","targets":[{"angle":2.52856,"distance":26.3877,"id":1294522,"speed":-0.55,"strength":13500600}],"timestamp":16554,"ui_units":"kmh"},{"json_units":"kmh","targets":[{"angle":2.41538,"distance":26.3702,"id":1294522,"speed":0.55,"strength":23587400}],"timestamp":16554,"ui_units":"kmh"},{"json_units":"kmh","targets":[{"angle":2.11617,"distance":26.2922,"id":1294522,"speed":-0.55,"strength":15311500}],"timestamp":16555,"ui_units":"kmh"},{"json_units":"kmh","targets":[{"angle":1.65794,"distance":26.0544,"id":1294522,"speed":-0.55,"strength":25944700}],"timestamp":16555,"ui_units":"kmh"},{"json_units":"kmh","targets":[{"angle":1.30862,"distance":25.9025,"id":1294522,"speed":0.55,"strength":17864500}],"timestamp":16555,"ui_units":"kmh"},{"json_units":"kmh","targets":[{"angle":1.24609,"distance":25.7561,"id":1294522,"speed":0.55,"strength":16311600}],"timestamp":16555,"ui_units":"kmh"},{"json_units":"kmh","targets":[{"angle":1.3213,"distance":25.801,"id":1294522,"speed":-0.55,"strength":25572600}],"timestamp":16556,"ui_units":"kmh"},{"json_units":"kmh","targets":[{"angle":1.4399,"distance":25.8577,"id":1294522,"speed":0.55,"strength":26490800}],"timestamp":16556,"ui_units":"kmh"},{"json_units":"kmh","targets":[{"angle":-0.994125,"distance":23.7902,"id":1294522,"speed":0.55,"strength":5169910}],"timestamp":16556,"ui_units":"kmh"},{"json_units":"kmh","targets":[{"angle":-1.5444,"distance":23.575,"id":1294522,"speed":-0.55,"strength":10700600}],"timestamp":16556,"ui_units":"kmh"},{"json_units":"kmh","targets":[{"angle":-1.19027,"distance":23.8616,"id":1294522,"speed":-0.55,"strength":37743300}],"timestamp":16557,"ui_units":"kmh"},{"json_units":"kmh","targets":[{"angle":-1.21215,"distance":23.9727,"id":1294522,"speed":0.55,"strength":29826800}],"timestamp":16557,"ui_units":"kmh"},{"json_units":"kmh","targets":[{"angle":-2.98953,"distance":22.3555,"id":1294522,"speed":0.55,"strength":4513770}],"timestamp":16557,"ui_units":"kmh"},{"json_units":"kmh","targets":[{"angle":-3.63674,"distance":21.8233,"id":1294522,"speed":-0.55,"strength":4306880}],"timestamp":16557,"ui_units":"kmh"},{"json_units":"kmh","targets":[{"angle":-2.83263,"distance":22.177,"id":1294522,"speed":0.55,"strength":48255300}],"timestamp":16558,"ui_units":"kmh"},{"json_units":"kmh","targets":[{"angle":-2.61201,"distance":22.6796,"id":1294522,"speed":0.55,"strength":28346000}],"timestamp":16558,"ui_units":"kmh"},{"json_units":"kmh","targets":[{"angle":-3.33767,"distance":22.5035,"id":1294522,"speed":-0.55,"strength":25974200}],"timestamp":16558,"ui_units":"kmh"},{"json_units":"kmh","targets":[{"angle":-3.07691,"distance":22.7608,"id":1294522,"speed":-0.55,"strength":24513600}],"timestamp":16558,"ui_units":"kmh"},{"json_units":"kmh","targets":[{"angle":-3.26421,"distance":22.6586,"id":1294522,"speed":-0.55,"strength":24513600}],"timestamp":16559,"ui_units":"kmh"},{"json_units":"kmh","targets":[{"angle":-0.495209,"distance":23.8286,"id":1294522,"speed":-0.55,"strength":6409360}],"timestamp":16559,"ui_units":"kmh"},{"json_units":"kmh","targets":[{"angle":3.07104,"distance":24.7777,"id":1294522,"speed":-0.55,"strength":14933200}],"timestamp":16559,"ui_units":"kmh"},{"json_units":"kmh","targets":[{"angle":5.0132,"distance":25.9767,"id":1294522,"speed":0.55,"strength":2279790}],"timestamp":16559,"ui_units":"kmh"},{"json_units":"kmh","targets":[{"angle":6.25578,"distance":27.5761,"id":1294522,"speed":0.55,"strength":17604400}],"timestamp":16560,"ui_units":"kmh"},{"json_units":"kmh","targets":[{"angle":6.39074,"distance":28.0005,"id":1294522,"speed":-0.55,"strength":20615200}],"timestamp":16560,"ui_units":"kmh"},{"json_units":"kmh","targets":[{"angle":6.19829,"distance":28.0215,"id":1294522,"speed":-0.55,"strength":11264400}],"timestamp":16560,"ui_units":"kmh"},{"json_units":"kmh","targets":[{"angle":5.97615,"distance":27.9372,"id":1294522,"speed":0.55,"strength":15275100}],"timestamp":16560,"ui_units":"kmh"},{"json_units":"kmh","targets":[{"angle":6.19963,"distance":28.1076,"id":1294522,"speed":0.55,"strength":15275100}],"timestamp":16561,"ui_units":"kmh"},{"json_units":"kmh","targets":[{"angle":5.53568,"distance":27.9947,"id":1294522,"speed":-0.55,"strength":17715400}],"timestamp":16561,"ui_units":"kmh"},{"json_units":"kmh","targets":[{"angle":5.21602,"distance":27.8399,"id":1294522,"speed":0.55,"strength":20287500}],"timestamp":16561,"ui_units":"kmh"},{"json_units":"kmh","targets":[{"angle":4.64841,"distance":27.5121,"id":1294522,"speed":0.55,"strength":14718200}],"timestamp":16561,"ui_units":"kmh"},{"json_units":"kmh","targets":[{"angle":4.73749,"distance":27.6027,"id":1294522,"speed":0.55,"strength":14718200}],"timestamp":16562,"ui_units":"kmh"},{"json_units":"kmh","targets":[{"angle":4.82598,"distance":27.6934,"id":1294522,"speed":0.55,"strength":14718200}],"timestamp":16562,"ui_units":"kmh"},{"json_units":"kmh","targets":[{"angle":4.19046,"distance":27.5054,"id":1294522,"speed":0.55,"strength":17242100}],"timestamp":16562,"ui_units":"kmh"},{"json_units":"kmh","targets":[{"angle":4.23384,"distance":27.5746,"id":1294522,"speed":0.55,"strength":17242100}],"timestamp":16562,"ui_units":"kmh"},{"json_units":"kmh","targets":[{"angle":3.9169,"distance":27.4734,"id":1294522,"speed":-3.14549,"strength":5949550}],"timestamp":16563,"ui_units":"kmh"},{"json_units":"kmh","targets":[{"angle":3.85374,"distance":27.6168,"id":1294522,"speed":-3.14549,"strength":5949550}],"timestamp":16563,"ui_units":"kmh"},{"json_units":"kmh","targets":[{"angle":4.03495,"distance":27.7702,"id":1294522,"speed":-4.19398,"strength":4987180}],"timestamp":16563,"ui_units":"kmh"},{"json_units":"kmh","targets":[{"angle":4.32102,"distance":27.802,"id":1294522,"speed":-0.55,"strength":10763000}],"timestamp":16563,"ui_units":"kmh"},{"json_units":"kmh","targets":[{"angle":4.52792,"distance":29.02,"id":1294522,"speed":0.55,"strength":5318170}],"timestamp":16564,"ui_units":"kmh"},{"json_units":"kmh","targets":[{"angle":5.66256,"distance":30.5064,"id":1294522,"speed":0.55,"strength":2851470}],"timestamp":16564,"ui_units":"kmh"},{"json_units":"kmh","targets":[{"angle":5.76443,"distance":30.8047,"id":1294522,"speed":-4.19398,"strength":4636360}],"timestamp":16564,"ui_units":"kmh"},{"json_units":"kmh","targets":[{"angle":5.81368,"distance":29.9983,"id":1294522,"speed":-0.55,"strength":15129800}],"timestamp":16564,"ui_units":"kmh"},{"json_units":"kmh","targets":[{"angle":5.20839,"distance":29.9755,"id":1294522,"speed":-3.14549,"strength":4250170}],"timestamp":16565,"ui_units":"kmh"},{"json_units":"kmh","targets":[{"angle":5.06251,"distance":30.9011,"id":1294522,"speed":0.55,"strength":16370800}],"timestamp":16565,"ui_units":"kmh"},{"json_units":"kmh","targets":[{"angle":3.97344,"distance":30.9429,"id":1294522,"speed":-0.55,"strength":9507820}],"timestamp":16565,"ui_units":"kmh"},{"json_units":"kmh","targets":[{"angle":3.4965,"distance":30.0108,"id":1294522,"speed":-0.55,"strength":12372600}],"timestamp":16565,"ui_units":"kmh"},{"json_units":"kmh","targets":[{"angle":3.43978,"distance":30.0901,"id":1294522,"speed":-0.55,"strength":12372600}],"timestamp":16566,"ui_units":"kmh"},{"json_units":"kmh","targets":[{"angle":2.93798,"distance":30.1709,"id":1294522,"speed":-0.55,"strength":9903660}],"timestamp":16566,"ui_units":"kmh"},{"json_units":"kmh","targets":[{"angle":2.52054,"distance":29.6828,"id":1294522,"speed":0.55,"strength":29932300}],"timestamp":16566,"ui_units":"kmh"},{"json_units":"kmh","targets":[{"angle":2.42231,"distance":29.7248,"id":1294522,"speed":0.55,"strength":29932300}],"timestamp":16566,"ui_units":"kmh"},{"json_units":"kmh","targets":[{"angle":1.88504,"distance":29.0983,"id":1294522,"speed":-0.55,"strength":20123400}],"timestamp":16567,"ui_units":"kmh"},{"json_units":"kmh","targets":[{"angle":1.29036,"distance":28.1678,"id":1294522,"speed":-0.55,"strength":21686400}],"timestamp":16567,"ui_units":"kmh"},{"json_units":"kmh","targets":[{"angle":0.894219,"distance":27.9374,"id":1294522,"speed":0.786372,"strength":9844590}],"timestamp":16567,"ui_units":"kmh"},{"json_units":"kmh","targets":[{"angle":2.90327,"distance":29.1637,"id":1294522,"speed":0.55,"strength":31730000}],"timestamp":16567,"ui_units":"kmh"},{"json_units":"kmh","targets":[{"angle":2.61896,"distance":28.6755,"id":1294522,"speed":-0.55,"strength":26949400}],"timestamp":16568,"ui_units":"kmh"},{"json_units":"kmh","targets":[{"angle":5.19018,"distance":29.9104,"id":1294522,"speed":0.55,"strength":2948240}],"timestamp":16568,"ui_units":"kmh"},{"json_units":"kmh","targets":[{"angle":7.60815,"distance":32.7038,"id":1294522,"speed":0.55,"strength":2289040}],"timestamp":16568,"ui_units":"kmh"},{"json_units":"kmh","targets":[{"angle":7.81717,"distance":32.9219,"id":1294522,"speed":0.55,"strength":2289040}],"timestamp":16568,"ui_units":"kmh"},{"json_units":"kmh","targets":[{"angle":6.66043,"distance":31.346,"id":1294522,"speed":-0.55,"strength":14571500}],"timestamp":16569,"ui_units":"kmh"},{"json_units":"kmh","targets":[{"angle":6.78826,"distance":31.4446,"id":1294522,"speed":-0.55,"strength":14571500}],"timestamp":16569,"ui_units":"kmh"},{"json_units":"kmh","targets":[{"angle":5.40099,"distance":29.8945,"id":1294522,"speed":0.55,"strength":4410630}],"timestamp":16569,"ui_units":"kmh"},{"json_units":"kmh","targets":[{"angle":5.43908,"distance":29.8905,"id":1294522,"speed":0.55,"strength":4410630}],"timestamp":16569,"ui_units":"kmh"},{"json_units":"kmh","targets":[{"angle":5.47718,"distance":29.8865,"id":1294522,"speed":0.55,"strength":4410630}],"timestamp":16570,"ui_units":"kmh"},{"json_units":"kmh","targets":[{"angle":5.19465,"distance":29.1796,"id":1294522,"speed":0.55,"strength":22217100}],"timestamp":16570,"ui_units":"kmh"},{"json_units":"kmh","targets":[{"angle":4.65791,"distance":28.5912,"id":1294522,"speed":-0.55,"strength":19030500}],"timestamp":16570,"ui_units":"kmh"},{"json_units":"kmh","targets":[{"angle":3.48319,"distance":27.639,"id":1294522,"speed":-0.55,"strength":31599200}],"timestamp":16570,"ui_units":"kmh"},{"json_units":"kmh","targets":[{"angle":3.01269,"distance":27.2535,"id":1294522,"speed":0.55,"strength":15254500}],"timestamp":16571,"ui_units":"kmh"},{"json_units":"kmh","targets":[{"angle":2.34657,"distance":27.4954,"id":1294522,"speed":-0.55,"strength":4201900}],"timestamp":16571,"ui_units":"kmh"},{"json_units":"kmh","targets":[{"angle":2.50463,"distance":27.1236,"id":1294522,"speed":-0.55,"strength":8922170}],"timestamp":16571,"ui_units":"kmh"},{"json_units":"kmh","targets":[{"angle":2.72222,"distance":26.8758,"id":1294522,"speed":0.55,"strength":7708930}],"timestamp":16571,"ui_units":"kmh"},{"json_units":"kmh","targets":[{"angle":3.89139,"distance":26.6284,"id":1294522,"speed":0.55,"strength":46521000}],"timestamp":16572,"ui_units":"kmh"},{"json_units":"kmh","targets":[{"angle":4.7047,"distance":26.3704,"id":1294522,"speed":-0.55,"strength":17653000}],"timestamp":16572,"ui_units":"kmh"},{"json_units":"kmh","targets":[{"angle":6.26034,"distance":25.9384,"id":1294522,"speed":-0.55,"strength":29334700}],"timestamp":16572,"ui_units":"kmh"},{"json_units":"kmh","targets":[{"angle":7.12881,"distance":25.7558,"id":1294522,"speed":0.55,"strength":25843900}],"timestamp":16572,"ui_units":"kmh"},{"json_units":"kmh","targets":[{"angle":8.2515,"distance":25.6099,"id":1294522,"speed":-0.55,"strength":18118900}],"timestamp":16573,"ui_units":"kmh"},{"json_units":"kmh","targets":[{"angle":10.1122,"distance":25.5056,"id":1294522,"speed":-0.55,"strength":14084000}],"timestamp":16573,"ui_units":"kmh"},{"json_units":"kmh","targets":[{"angle":10.4618,"distance":25.3769,"id":1294522,"speed":-0.55,"strength":14084000}],"timestamp":16573,"ui_units":"kmh"},{"json_units":"kmh","targets":[{"angle":12.2247,"distance":25.1507,"id":1294522,"speed":-0.55,"strength":10765900}],"timestamp":16573,"ui_units":"kmh"},{"json_units":"kmh","targets":[{"angle":12.6522,"distance":25.03,"id":1294522,"speed":-0.55,"strength":10765900}],"timestamp":16574,"ui_units":"kmh"},{"json_units":"kmh","targets":[{"angle":16.4594,"distance":27.0736,"id":1294522,"speed":0.55,"strength":1197610}],"timestamp":16574,"ui_units":"kmh"},{"json_units":"kmh","targets":[{"angle":16.292,"distance":26.8403,"id":1294522,"speed":-3.66974,"strength":1060050}],"timestamp":16574,"ui_units":"kmh"},{"json_units":"kmh","targets":[{"angle":16.8206,"distance":26.8514,"id":1294522,"speed":-3.66974,"strength":1060050}],"timestamp":16574,"ui_units":"kmh"},{"json_units":"kmh","targets":[{"angle":17.8764,"distance":26.8805,"id":1294522,"speed":-3.66974,"strength":1060050}],"timestamp":16575,"ui_units":"kmh"},{"json_units":"kmh","targets":[{"angle":18.4033,"distance":26.8985,"id":1294522,"speed":-3.66974,"strength":1060050}],"timestamp":16575,"ui_units":"kmh"},{"json_units":"kmh","targets":[{"angle":19.2399,"distance":25.7059,"id":1294522,"speed":0.55,"strength":6803970}],"timestamp":16575,"ui_units":"kmh"},{"json_units":"kmh","targets":[{"angle":19.0611,"distance":25.6464,"id":1294522,"speed":-0.55,"strength":14489800}],"timestamp":16575,"ui_units":"kmh"},{"json_units":"kmh","targets":[{"angle":18.232,"distance":25.9409,"id":1294522,"speed":-0.55,"strength":21242900}],"timestamp":16576,"ui_units":"kmh"},{"json_units":"kmh","targets":[{"angle":17.6978,"distance":25.9623,"id":1294522,"speed":0.55,"strength":27175600}],"timestamp":16576,"ui_units":"kmh"},{"json_units":"kmh","targets":[{"angle":17.3227,"distance":26.2458,"id":1294522,"speed":0.55,"strength":34878900}],"timestamp":16576,"ui_units":"kmh"},{"json_units":"kmh","targets":[{"angle":16.7321,"distance":26.4125,"id":1294522,"speed":-1.06137,"strength":25050500}],"timestamp":16576,"ui_units":"kmh"},{"json_units":"kmh","targets":[{"angle":16.1807,"distance":26.6473,"id":1294522,"speed":0.55,"strength":23063200}],"timestamp":16577,"ui_units":"kmh"},{"json_units":"kmh","targets":[{"angle":15.5333,"distance":26.5574,"id":1294522,"speed":0.55,"strength":16248200}],"timestamp":16577,"ui_units":"kmh"},{"json_units":"kmh","targets":[{"angle":15.2107,"distance":26.5847,"id":1294522,"speed":-0.55,"strength":19445600}],"timestamp":16577,"ui_units":"kmh"},{"json_units":"kmh","targets":[{"angle":14.5051,"distance":26.8386,"id":1294522,"speed":-0.55,"strength":31522400}],"timestamp":16577,"ui_units":"kmh"},{"json_units":"kmh","targets":[{"angle":13.7431,"distance":26.6838,"id":1294522,"speed":0.55,"strength":15057900}],"timestamp":16578,"ui_units":"kmh"},{"json_units":"kmh","targets":[{"angle":12.7374,"distance":26.4775,"id":1294522,"speed":-0.55,"strength":24286600}],"timestamp":16578,"ui_units":"kmh"},{"json_units":"kmh","targets":[{"angle":10.7847,"distance":26.3227,"id":1294522,"speed":-0.55,"strength":28091400}],"timestamp":16578,"ui_units":"kmh"},{"json_units":"kmh","targets":[{"angle":11.1611,"distance":25.6231,"id":1294522,"speed":0.55,"strength":5132360}],"timestamp":16578,"ui_units":"kmh"},{"json_units":"kmh","targets":[{"angle":9.045870000000001,"distance":26.297,"id":1294522,"speed":0.55,"strength":18679100}],"timestamp":16579,"ui_units":"kmh"},{"json_units":"kmh","targets":[{"angle":9.33569,"distance":25.3361,"id":1294522,"speed":-0.55,"strength":4466260}],"timestamp":16579,"ui_units":"kmh"},{"json_units":"kmh","targets":[{"angle":8.719139999999999,"distance":25.3594,"id":1294522,"speed":0.55,"strength":27786500}],"timestamp":16579,"ui_units":"kmh"},{"json_units":"kmh","targets":[{"angle":6.85605,"distance":25.3731,"id":1294522,"speed":0.55,"strength":37675700}],"timestamp":16579,"ui_units":"kmh"},{"json_units":"kmh","targets":[{"angle":6.10181,"distance":25.4325,"id":1294522,"speed":-0.55,"strength":33692600}],"timestamp":16580,"ui_units":"kmh"},{"json_units":"kmh","targets":[{"angle":6.16237,"distance":24.6741,"id":1294522,"speed":-3.66974,"strength":2790270}],"timestamp":16580,"ui_units":"kmh"},{"json_units":"kmh","targets":[{"angle":5.83908,"distance":24.5973,"id":1294522,"speed":-3.66974,"strength":2790270}],"timestamp":16580,"ui_units":"kmh"},{"json_units":"kmh","targets":[{"angle":5.51377,"distance":24.5213,"id":1294522,"speed":-3.66974,"strength":2790270}],"timestamp":16580,"ui_units":"kmh"},{"json_units":"kmh","targets":[{"angle":3.54588,"distance":24.4925,"id":1294522,"speed":-0.55,"strength":27474600}],"timestamp":16581,"ui_units":"kmh"},{"json_units":"kmh","targets":[{"angle":2.8796,"distance":24.8085,"id":1294522,"speed":0.55,"strength":27913500}],"timestamp":16581,"ui_units":"kmh"},{"json_units":"kmh","targets":[{"angle":1.50598,"distance":25.0521,"id":1294522,"speed":-0.55,"strength":36463700}],"timestamp":16581,"ui_units":"kmh"},{"json_units":"kmh","targets":[{"angle":2.79075,"distance":26.7553,"id":1294522,"speed":-0.55,"strength":3952560}],"timestamp":16581,"ui_units":"kmh"},{"json_units":"kmh","targets":[{"angle":2.18051,"distance":26.7594,"id":1294522,"speed":-0.55,"strength":23534100}],"timestamp":16582,"ui_units":"kmh"},{"json_units":"kmh","targets":[{"angle":1.69842,"distance":26.6304,"id":1294522,"speed":0.55,"strength":30445200}],"timestamp":16582,"ui_units":"kmh"},{"json_units":"kmh","targets":[{"angle":1.40536,"distance":26.5568,"id":1294522,"speed":-0.55,"strength":34119300}],"timestamp":16582,"ui_units":"kmh"},{"json_units":"kmh","targets":[{"angle":0.537053,"distance":26.4946,"id":1294522,"speed":-0.55,"strength":21400100}],"timestamp":16582,"ui_units":"kmh"},{"json_units":"kmh","targets":[{"angle":0.245038,"distance":26.8833,"id":1294522,"speed":0.55,"strength":11781400}],"timestamp":16583,"ui_units":"kmh"},{"json_units":"kmh","targets":[{"angle":-0.078694,"distance":26.8907,"id":1294522,"speed":0.55,"strength":36936600}],"timestamp":16583,"ui_units":"kmh"},{"json_units":"kmh","targets":[{"angle":-0.233381,"distance":26.8419,"id":1294522,"speed":-0.55,"strength":20841100}],"timestamp":16583,"ui_units":"kmh"},{"json_units":"kmh","targets":[{"angle":-0.626816,"distance":28.0461,"id":1294522,"speed":-0.55,"strength":18592300}],"timestamp":16583,"ui_units":"kmh"},{"json_units":"kmh","targets":[{"angle":-0.624074,"distance":27.8237,"id":1294522,"speed":0.55,"strength":15327900}],"timestamp":16584,"ui_units":"kmh"},{"json_units":"kmh","targets":[{"angle":-0.887007,"distance":27.9183,"id":1294522,"speed":0.55,"strength":15327900}],"timestamp":16584,"ui_units":"kmh"},{"json_units":"kmh","targets":[{"angle":-1.11779,"distance":28.2442,"id":1294522,"speed":-0.55,"strength":12921800}],"timestamp":16584,"ui_units":"kmh"},{"json_units":"kmh","targets":[{"angle":-0.683568,"distance":28.0601,"id":1294522,"speed":0.55,"strength":38017500}],"timestamp":16584,"ui_units":"kmh"},{"json_units":"kmh","targets":[{"angle":-0.0366744,"distance":27.7358,"id":1294522,"speed":0.55,"strength":36653500}],"timestamp":16585,"ui_units":"kmh"},{"json_units":"kmh","targets":[{"angle":0.240471,"distance":27.8308,"id":1294522,"speed":-0.55,"strength":10526600}],"timestamp":16585,"ui_units":"kmh"},{"json_units":"kmh","targets":[{"angle":1.11759,"distance":28.1912,"id":1294522,"speed":-0.55,"strength":14495600}],"timestamp":16585,"ui_units":"kmh"},{"json_units":"kmh","targets":[{"angle":1.36173,"distance":28.0869,"id":1294522,"speed":0.55,"strength":10212900}],"timestamp":16585,"ui_units":"kmh"},{"json_units":"kmh","targets":[{"angle":2.61323,"distance":27.2877,"id":1294522,"speed":0.55,"strength":5155920}],"timestamp":16586,"ui_units":"kmh"},{"json_units":"kmh","targets":[{"angle":3.40076,"distance":26.7637,"id":1294522,"speed":-0.55,"strength":4713280}],"timestamp":16586,"ui_units":"kmh"},{"json_units":"kmh","targets":[{"angle":4.17028,"distance":26.5601,"id":1294522,"speed":0.55,"strength":8283810}],"timestamp":16586,"ui_units":"kmh"},{"json_units":"kmh","targets":[{"angle":5.18802,"distance":26.8528,"id":1294522,"speed":0.55,"strength":21373800}],"timestamp":16586,"ui_units":"kmh"},{"json_units":"kmh","targets":[{"angle":6.1907,"distance":26.9982,"id":1294522,"speed":-0.55,"strength":15162100}],"timestamp":16587,"ui_units":"kmh"},{"json_units":"kmh","targets":[{"angle":8.266870000000001,"distance":26.353,"id":1294522,"speed":-0.55,"strength":4014660}],"timestamp":16587,"ui_units":"kmh"},{"json_units":"kmh","targets":[{"angle":8.602449999999999,"distance":26.315,"id":1294522,"speed":-0.55,"strength":4014660}],"timestamp":16587,"ui_units":"kmh"},{"json_units":"kmh","targets":[{"angle":9.276479999999999,"distance":26.2417,"id":1294522,"speed":-0.55,"strength":4014660}],"timestamp":16587,"ui_units":"kmh"},{"json_units":"kmh","targets":[{"angle":9.614879999999999,"distance":26.2065,"id":1294522,"speed":-0.55,"strength":4014660}],"timestamp":16588,"ui_units":"kmh"},{"json_units":"kmh","targets":[{"angle":9.954190000000001,"distance":26.1721,"id":1294522,"speed":-0.55,"strength":4014660}],"timestamp":16588,"ui_units":"kmh"},{"json_units":"kmh","targets":[{"angle":10.6354,"distance":26.1062,"id":1294522,"speed":-0.55,"strength":4014660}],"timestamp":16588,"ui_units":"kmh"},{"json_units":"kmh","targets":[{"angle":10.9773,"distance":26.0746,"id":1294522,"speed":-0.55,"strength":4014660}],"timestamp":16588,"ui_units":"kmh"},{"json_units":"kmh","targets":[{"angle":11.4957,"distance":25.6043,"id":1294522,"speed":-0.55,"strength":8636280}],"timestamp":16589,"ui_units":"kmh"},{"json_units":"kmh","targets":[{"angle":12.1723,"distance":25.115,"id":1294522,"speed":0.55,"strength":15930500}],"timestamp":16589,"ui_units":"kmh"},{"json_units":"kmh","targets":[{"angle":12.9084,"distance":24.9722,"id":1294522,"speed":0.55,"strength":15930500}],"timestamp":16589,"ui_units":"kmh"},{"json_units":"kmh","targets":[{"angle":12.4456,"distance":25.6836,"id":1294522,"speed":-0.55,"strength":7775200}],"timestamp":16589,"ui_units":"kmh"},{"json_units":"kmh","targets":[{"angle":12.2771,"distance":25.3262,"id":1294522,"speed":0.55,"strength":20802400}],"timestamp":16590,"ui_units":"kmh"},{"json_units":"kmh","targets":[{"angle":12.1466,"distance":24.8468,"id":1294522,"speed":0.55,"strength":11318600}],"timestamp":16590,"ui_units":"kmh"},{"json_units":"kmh","targets":[{"angle":12.0203,"distance":24.6898,"id":1294522,"speed":-0.55,"strength":14282200}],"timestamp":16590,"ui_units":"kmh"},{"json_units":"kmh","targets":[{"angle":9.63815,"distance":26.388,"id":1294522,"speed":-0.55,"strength":5194110}],"timestamp":16590,"ui_units":"kmh"},{"json_units":"kmh","targets":[{"angle":8.77467,"distance":27.8199,"id":1294522,"speed":0.55,"strength":6327420}],"timestamp":16591,"ui_units":"kmh"},{"json_units":"kmh","targets":[{"angle":7.99929,"distance":27.4479,"id":1294522,"speed":-0.55,"strength":34357600}],"timestamp":16591,"ui_units":"kmh"},{"json_units":"kmh","targets":[{"angle":6.05897,"distance":28.5171,"id":1294522,"speed":-0.55,"strength":6757470}],"timestamp":16591,"ui_units":"kmh"},{"json_units":"kmh","targets":[{"angle":5.72033,"distance":29.1529,"id":1294522,"speed":0.55,"strength":4873260}],"timestamp":16591,"ui_units":"kmh"},{"json_units":"kmh","targets":[{"angle":4.5339,"distance":28.3865,"id":1294522,"speed":0.55,"strength":17994300}],"timestamp":16592,"ui_units":"kmh"},{"json_units":"kmh","targets":[{"angle":4.20957,"distance":27.9557,"id":1294522,"speed":-0.55,"strength":15822100}],"timestamp":16592,"ui_units":"kmh"},{"json_units":"kmh","targets":[{"angle":3.35819,"distance":27.9799,"id":1294522,"speed":-0.55,"strength":22787000}],"timestamp":16592,"ui_units":"kmh"},{"json_units":"kmh","targets":[{"angle":2.89759,"distance":27.9206,"id":1294522,"speed":0.55,"strength":11634900}],"timestamp":16592,"ui_units":"kmh"},{"json_units":"kmh","targets":[{"angle":2.60783,"distance":27.9525,"id":1294522,"speed":-0.55,"strength":7862580}],"timestamp":16593,"ui_units":"kmh"},{"json_units":"kmh","targets":[{"angle":1.80577,"distance":28.7194,"id":1294522,"speed":-0.55,"strength":6320350}],"timestamp":16593,"ui_units":"kmh"},{"json_units":"kmh","targets":[{"angle":1.44333,"distance":28.4321,"id":1294522,"speed":0.55,"strength":20132000}],"timestamp":16593,"ui_units":"kmh"},{"json_units":"kmh","targets":[{"angle":0.520774,"distance":27.8962,"id":1294522,"speed":0.55,"strength":24541600}],"timestamp":16593,"ui_units":"kmh"},{"json_units":"kmh","targets":[{"angle":0.349407,"distance":27.7385,"id":1294522,"speed":-1.06137,"strength":24418700}],"timestamp":16594,"ui_units":"kmh"},{"json_units":"kmh","targets":[{"angle":0.545562,"distance":28.7131,"id":1294522,"speed":0.55,"strength":3650200}],"timestamp":16594,"ui_units":"kmh"},{"json_units":"kmh","targets":[{"angle":0.665013,"distance":29.549,"id":1294522,"speed":4.71823,"strength":4547150}],"timestamp":16594,"ui_units":"kmh"},{"json_units":"kmh","targets":[{"angle":0.474037,"distance":29.6708,"id":1294522,"speed":4.71823,"strength":4547150}],"timestamp":16594,"ui_units":"kmh"},{"json_units":"kmh","targets":[{"angle":0.0189502,"distance":28.7792,"id":1294522,"speed":-0.55,"strength":40791100}],"timestamp":16595,"ui_units":"kmh"},{"json_units":"kmh","targets":[{"angle":-0.251671,"distance":28.4134,"id":1294522,"speed":0.55,"strength":35579600}],"timestamp":16595,"ui_units":"kmh"},{"json_units":"kmh","targets":[{"angle":-0.400618,"distance":28.4546,"id":1294522,"speed":-0.55,"strength":19085900}],"timestamp":16595,"ui_units":"kmh"},{"json_units":"kmh","targets":[{"angle":-0.544123,"distance":28.2723,"id":1294522,"speed":-0.55,"strength":32552800}],"timestamp":16595,"ui_units":"kmh"},{"json_units":"kmh","targets":[{"angle":-0.706805,"distance":27.9518,"id":1294522,"speed":0.55,"strength":40522500}],"timestamp":16596,"ui_units":"kmh"},{"json_units":"kmh","targets":[{"angle":-0.8181079999999999,"distance":27.5132,"id":1294522,"speed":0.55,"strength":17195900}],"timestamp":16596,"ui_units":"kmh"},{"json_units":"kmh","targets":[{"angle":-0.723206,"distance":27.25,"id":1294522,"speed":-0.55,"strength":24116600}],"timestamp":16596,"ui_units":"kmh"},{"json_units":"kmh","targets":[{"angle":-0.670323,"distance":26.8338,"id":1294522,"speed":-0.55,"strength":30616400}],"timestamp":16596,"ui_units":"kmh"},{"json_units":"kmh","targets":[{"angle":-0.709865,"distance":26.6274,"id":1294522,"speed":0.55,"strength":33325400}],"timestamp":16597,"ui_units":"kmh"},{"json_units":"kmh","targets":[{"angle":-0.625497,"distance":26.4375,"id":1294522,"speed":-0.55,"strength":34157200}],"timestamp":16597,"ui_units":"kmh"},{"json_units":"kmh","targets":[{"angle":-0.390934,"distance":26.2977,"id":1294522,"speed":-0.55,"strength":25094400}],"timestamp":16597,"ui_units":"kmh"},{"json_units":"kmh","targets":[{"angle":-0.175193,"distance":26.141,"id":1294522,"speed":0.55,"strength":32311600}],"timestamp":16597,"ui_units":"kmh"},{"json_units":"kmh","targets":[{"angle":0.653172,"distance":26.4693,"id":1294522,"speed":0.55,"strength":46734700}],"timestamp":16598,"ui_units":"kmh"},{"json_units":"kmh","targets":[{"angle":0.94421,"distance":26.3886,"id":1294522,"speed":-0.55,"strength":25032600}],"timestamp":16598,"ui_units":"kmh"},{"json_units":"kmh","targets":[{"angle":0.939438,"distance":26.244,"id":1294522,"speed":0.55,"strength":40594500}],"timestamp":16598,"ui_units":"kmh"},{"json_units":"kmh","targets":[{"angle":1.2206,"distance":26.1857,"id":1294522,"speed":0.55,"strength":35630300}],"timestamp":16598,"ui_units":"kmh"},{"json_units":"kmh","targets":[{"angle":1.46019,"distance":26.1879,"id":1294522,"speed":-0.55,"strength":26979700}],"timestamp":16599,"ui_units":"kmh"},{"json_units":"kmh","targets":[{"angle":1.69618,"distance":25.9369,"id":1294522,"speed":-0.55,"strength":40609100}],"timestamp":16599,"ui_units":"kmh"},{"json_units":"kmh","targets":[{"angle":1.75804,"distance":25.966,"id":1294522,"speed":0.55,"strength":56861500}],"timestamp":16599,"ui_units":"kmh"},{"json_units":"kmh","targets":[{"angle":1.92511,"distance":25.9466,"id":1294522,"speed":-0.55,"strength":40326000}],"timestamp":16599,"ui_units":"kmh"},{"json_units":"kmh","targets":[{"angle":1.77702,"distance":26.0071,"id":1294522,"speed":-0.55,"strength":22138000}],"timestamp":16600,"ui_units":"kmh"},{"json_units":"kmh","targets":[{"angle":2.28116,"distance":26.4883,"id":1294522,"speed":0.55,"strength":4732820}],"timestamp":16600,"ui_units":"kmh"},{"json_units":"kmh","targets":[{"angle":1.89269,"distance":26.2626,"id":1294522,"speed":0.55,"strength":35700400}],"timestamp":16600,"ui_units":"kmh"},{"json_units":"kmh","targets":[{"angle":1.68452,"distance":26.1617,"id":1294522,"speed":-0.55,"strength":26113600}],"timestamp":16600,"ui_units":"kmh"},{"json_units":"kmh","targets":[{"angle":1.56453,"distance":25.9361,"id":1294522,"speed":-0.55,"strength":20792500}],"timestamp":16601,"ui_units":"kmh"},{"json_units":"kmh","targets":[{"angle":1.56701,"distance":25.9497,"id":1294522,"speed":1.06137,"strength":20882200}],"timestamp":16601,"ui_units":"kmh"},{"json_units":"kmh","targets":[{"angle":1.99078,"distance":25.5209,"id":1294522,"speed":0.55,"strength":26462900}],"timestamp":16601,"ui_units":"kmh"},{"json_units":"kmh","targets":[{"angle":2.10774,"distance":25.4803,"id":1294522,"speed":-0.55,"strength":27361700}],"timestamp":16601,"ui_units":"kmh"},{"json_units":"kmh","targets":[{"angle":2.69821,"distance":26.7123,"id":1294522,"speed":-0.55,"strength":15458800}],"timestamp":16602,"ui_units":"kmh"},{"json_units":"kmh","targets":[{"angle":3.23215,"distance":27.7987,"id":1294522,"speed":0.55,"strength":18126500}],"timestamp":16602,"ui_units":"kmh"},{"json_units":"kmh","targets":[{"angle":3.82546,"distance":27.8146,"id":1294522,"speed":3.14549,"strength":14141400}],"timestamp":16602,"ui_units":"kmh"},{"json_units":"kmh","targets":[{"angle":4.92557,"distance":28.0319,"id":1294522,"speed":0.55,"strength":22519500}],"timestamp":16603,"ui_units":"kmh"},{"json_units":"kmh","targets":[{"angle":5.09631,"distance":28.1269,"id":1294522,"speed":0.55,"strength":22519500}],"timestamp":16603,"ui_units":"kmh"},{"json_units":"kmh","targets":[{"angle":6.02032,"distance":27.3205,"id":1294522,"speed":-3.66974,"strength":15498000}],"timestamp":16603,"ui_units":"kmh"},{"json_units":"kmh","targets":[{"angle":6.93405,"distance":27.4517,"id":1294522,"speed":-0.55,"strength":35023300}],"timestamp":16603,"ui_units":"kmh"},{"json_units":"kmh","targets":[{"angle":8.145300000000001,"distance":27.8522,"id":1294522,"speed":-0.55,"strength":17068700}],"timestamp":16604,"ui_units":"kmh"},{"json_units":"kmh","targets":[{"angle":8.430529999999999,"distance":27.918,"id":1294522,"speed":-0.55,"strength":17068700}],"timestamp":16604,"ui_units":"kmh"},{"json_units":"kmh","targets":[{"angle":8.714399999999999,"distance":27.9844,"id":1294522,"speed":-0.55,"strength":17068700}],"timestamp":16604,"ui_units":"kmh"},{"json_units":"kmh","targets":[{"angle":9.008789999999999,"distance":29.5853,"id":1294522,"speed":-0.55,"strength":5034700}],"timestamp":16604,"ui_units":"kmh"},{"json_units":"kmh","targets":[{"angle":9.26003,"distance":29.7401,"id":1294522,"speed":-0.55,"strength":5034700}],"timestamp":16605,"ui_units":"kmh"},{"json_units":"kmh","targets":[{"angle":9.75474,"distance":30.0514,"id":1294522,"speed":-0.55,"strength":5034700}],"timestamp":16605,"ui_units":"kmh"},{"json_units":"kmh","targets":[{"angle":9.99826,"distance":30.2079,"id":1294522,"speed":-0.55,"strength":5034700}],"timestamp":16605,"ui_units":"kmh"},{"json_units":"kmh","targets":[{"angle":9.84009,"distance":32.072,"id":1294522,"speed":0.55,"strength":2770560}],"timestamp":16605,"ui_units":"kmh"},{"json_units":"kmh","targets":[{"angle":10.0423,"distance":31.938,"id":1294522,"speed":0.55,"strength":8680100}],"timestamp":16606,"ui_units":"kmh"},{"json_units":"kmh","targets":[{"angle":8.87627,"distance":31.0676,"id":1294522,"speed":-3.93186,"strength":4871910}],"timestamp":16606,"ui_units":"kmh"},{"json_units":"kmh","targets":[{"angle":7.12928,"distance":30.2488,"id":1294522,"speed":-4.19398,"strength":5933430}],"timestamp":16606,"ui_units":"kmh"},{"json_units":"kmh","targets":[{"angle":6.47596,"distance":29.9288,"id":1294522,"speed":-3.66974,"strength":4197160}],"timestamp":16606,"ui_units":"kmh"},{"json_units":"kmh","targets":[{"angle":5.7795,"distance":29.6018,"id":1294522,"speed":-4.19398,"strength":17597500}],"timestamp":16607,"ui_units":"kmh"},{"json_units":"kmh","targets":[{"angle":5.54936,"distance":29.104,"id":1294522,"speed":-4.19398,"strength":11129500}],"timestamp":16607,"ui_units":"kmh"},{"json_units":"kmh","targets":[{"angle":5.49113,"distance":29.2968,"id":1294522,"speed":-5.24248,"strength":5993290}],"timestamp":16607,"ui_units":"kmh"},{"json_units":"kmh","targets":[{"angle":5.2514,"distance":29.0079,"id":1294522,"speed":-3.66974,"strength":8700650}],"timestamp":16607,"ui_units":"kmh"},{"json_units":"kmh","targets":[{"angle":5.55541,"distance":28.5364,"id":1294522,"speed":-4.19398,"strength":10062400}],"timestamp":16608,"ui_units":"kmh"},{"json_units":"kmh","targets":[{"angle":5.92878,"distance":27.8289,"id":1294522,"speed":-3.66974,"strength":5807780}],"timestamp":16608,"ui_units":"kmh"},{"json_units":"kmh","targets":[{"angle":5.90559,"distance":27.294,"id":1294522,"speed":-3.93186,"strength":11407100}],"timestamp":16608,"ui_units":"kmh"},{"json_units":"kmh","targets":[{"angle":5.82039,"distance":26.3207,"id":1294522,"speed":-3.14549,"strength":13972000}],"timestamp":16608,"ui_units":"kmh"},{"json_units":"kmh","targets":[{"angle":5.68759,"distance":25.6902,"id":1294522,"speed":-3.14549,"strength":10491400}],"timestamp":16609,"ui_units":"kmh"},{"json_units":"kmh","targets":[{"angle":5.72126,"distance":25.4341,"id":1294522,"speed":-3.66974,"strength":6307100}],"timestamp":16609,"ui_units":"kmh"},{"json_units":"kmh","targets":[{"angle":5.43848,"distance":24.2888,"id":1294522,"speed":-3.66974,"strength":13421900}],"timestamp":16609,"ui_units":"kmh"},{"json_units":"kmh","targets":[{"angle":5.75868,"distance":24.023,"id":1294522,"speed":-4.19398,"strength":6914300}],"timestamp":16609,"ui_units":"kmh"},{"json_units":"kmh","targets":[{"angle":5.5627,"distance":23.1224,"id":1294522,"speed":-4.19398,"strength":10250000}],"timestamp":16610,"ui_units":"kmh"},{"json_units":"kmh","targets":[{"angle":5.85942,"distance":22.8442,"id":1294522,"speed":-4.19398,"strength":6849940}],"timestamp":16610,"ui_units":"kmh"},{"json_units":"kmh","targets":[{"angle":5.40597,"distance":21.8685,"id":1294522,"speed":-3.66974,"strength":10378200}],"timestamp":16610,"ui_units":"kmh"},{"json_units":"kmh","targets":[{"angle":5.31232,"distance":21.5652,"id":1294522,"speed":-3.66974,"strength":7692890}],"timestamp":16610,"ui_units":"kmh"},{"json_units":"kmh","targets":[{"angle":5.0694,"distance":20.9179,"id":1294522,"speed":-3.66974,"strength":3145940}],"timestamp":16611,"ui_units":"kmh"},{"json_units":"kmh","targets":[{"angle":5.23676,"distance":20.6969,"id":1294522,"speed":-3.66974,"strength":3145940}],"timestamp":16611,"ui_units":"kmh"},{"json_units":"kmh","targets":[{"angle":4.81155,"distance":20.2527,"id":1294522,"speed":-3.14549,"strength":3556830}],"timestamp":16611,"ui_units":"kmh"},{"json_units":"kmh","targets":[{"angle":2.98502,"distance":19.7643,"id":1294522,"speed":-3.14549,"strength":3881420}],"timestamp":16611,"ui_units":"kmh"},{"json_units":"kmh","targets":[{"angle":2.52521,"distance":19.6574,"id":1294522,"speed":-3.14549,"strength":3045720}],"timestamp":16612,"ui_units":"kmh"},{"json_units":"kmh","targets":[{"angle":1.29277,"distance":18.6506,"id":1294522,"speed":-4.71823,"strength":1942860}],"timestamp":16612,"ui_units":"kmh"},{"json_units":"kmh","targets":[{"angle":0.616833,"distance":18.5129,"id":1294522,"speed":-5.76673,"strength":1277330}],"timestamp":16612,"ui_units":"kmh"},{"json_units":"kmh","targets":[{"angle":0.27309,"distance":18.2247,"id":1294522,"speed":-5.76673,"strength":1277330}],"timestamp":16612,"ui_units":"kmh"},{"json_units":"kmh","targets":[{"angle":-0.448001,"distance":17.6505,"id":1294522,"speed":-5.76673,"strength":1277330}],"timestamp":16613,"ui_units":"kmh"},{"json_units":"kmh","targets":[{"angle":-0.826402,"distance":17.3644,"id":1294522,"speed":-5.76673,"strength":1277330}],"timestamp":16613,"ui_units":"kmh"},{"json_units":"kmh","targets":[{"angle":5.06417,"distance":19.7906,"id":1294522,"speed":-4.71823,"strength":759516}],"timestamp":16613,"ui_units":"kmh"},{"json_units":"kmh","targets":[{"angle":5.14481,"distance":19.6764,"id":1294522,"speed":-4.71823,"strength":759516}],"timestamp":16613,"ui_units":"kmh"},{"json_units":"kmh","targets":[{"angle":1.33877,"distance":20.3369,"id":1294522,"speed":-0.786372,"strength":16068900}],"timestamp":16614,"ui_units":"kmh"},{"json_units":"kmh","targets":[{"angle":1.18533,"distance":20.273,"id":1294522,"speed":-0.786372,"strength":16068900}],"timestamp":16614,"ui_units":"kmh"},{"json_units":"kmh","targets":[{"angle":-3.02779,"distance":20.7617,"id":1294522,"speed":-0.55,"strength":6773430}],"timestamp":16614,"ui_units":"kmh"},{"json_units":"kmh","targets":[{"angle":-5.29397,"distance":21.2148,"id":1294522,"speed":0.55,"strength":6003110}],"timestamp":16614,"ui_units":"kmh"},{"json_units":"kmh","targets":[{"angle":-5.74641,"distance":21.2208,"id":1294522,"speed":0.55,"strength":6003110}],"timestamp":16615,"ui_units":"kmh"},{"json_units":"kmh","targets":[{"angle":-6.65038,"distance":21.2368,"id":1294522,"speed":0.55,"strength":6003110}],"timestamp":16615,"ui_units":"kmh"},{"json_units":"kmh","targets":[{"angle":-7.10181,"distance":21.2467,"id":1294522,"speed":0.55,"strength":6003110}],"timestamp":16615,"ui_units":"kmh"},{"json_units":"kmh","targets":[{"angle":-3.02597,"distance":17.8144,"id":1294522,"speed":0.55,"strength":1062170}],"timestamp":16615,"ui_units":"kmh"},{"json_units":"kmh","targets":[{"angle":-3.26618,"distance":17.6419,"id":1294522,"speed":0.55,"strength":1062170}],"timestamp":16616,"ui_units":"kmh"},{"json_units":"kmh","targets":[{"angle":0.623306,"distance":15.0622,"id":1294522,"speed":0.55,"strength":1340040}],"timestamp":16616,"ui_units":"kmh"},{"json_units":"kmh","targets":[{"angle":0.623839,"distance":14.4722,"id":1294522,"speed":0.55,"strength":1340040}],"timestamp":16616,"ui_units":"kmh"},{"json_units":"kmh","targets":[{"angle":5.41741,"distance":17.4672,"id":1294522,"speed":-0.55,"strength":5484480}],"timestamp":16616,"ui_units":"kmh"},{"json_units":"kmh","targets":[{"angle":5.96978,"distance":17.2084,"id":1294522,"speed":-0.55,"strength":5484480}],"timestamp":16617,"ui_units":"kmh"},{"json_units":"kmh","targets":[{"angle":6.25222,"distance":17.0796,"id":1294522,"speed":-0.55,"strength":5484480}],"timestamp":16617,"ui_units":"kmh"},{"json_units":"kmh","targets":[{"angle":9.30186,"distance":13.9991,"id":1294522,"speed":0.55,"strength":1111060}],"timestamp":16617,"ui_units":"kmh"},{"json_units":"kmh","targets":[{"angle":9.82715,"distance":13.7425,"id":1294522,"speed":0.55,"strength":1111060}],"timestamp":16617,"ui_units":"kmh"},{"json_units":"kmh","targets":[{"angle":17.4917,"distance":14.3618,"id":1294522,"speed":0.55,"strength":1072780}],"timestamp":16618,"ui_units":"kmh"},{"json_units":"kmh","targets":[{"angle":19.4584,"distance":13.989,"id":1294522,"speed":0.55,"strength":1072780}],"timestamp":16618,"ui_units":"kmh"},{"json_units":"kmh","targets":[{"angle":20.4809,"distance":13.809,"id":1294522,"speed":0.55,"strength":1072780}],"timestamp":16618,"ui_units":"kmh"},{"json_units":"kmh","targets":[{"angle":25.5202,"distance":16.462,"id":1294522,"speed":0.55,"strength":1244350}],"timestamp":16618,"ui_units":"kmh"},{"json_units":"kmh","targets":[{"angle":26.5475,"distance":16.444,"id":1294522,"speed":0.55,"strength":1244350}],"timestamp":16619,"ui_units":"kmh"},{"json_units":"kmh","targets":[{"angle":27.5766,"distance":16.4312,"id":1294522,"speed":0.55,"strength":1244350}],"timestamp":16619,"ui_units":"kmh"},{"json_units":"kmh","targets":[{"angle":30.1316,"distance":13.6265,"id":1294522,"speed":-0.55,"strength":990529}],"timestamp":16619,"ui_units":"kmh"},{"json_units":"kmh","targets":[{"angle":31.4105,"distance":13.5068,"id":1294522,"speed":-0.55,"strength":990529}],"timestamp":16619,"ui_units":"kmh"},{"json_units":"kmh","targets":[{"angle":32.7117,"distance":13.394,"id":1294522,"speed":-0.55,"strength":990529}],"timestamp":16619,"ui_units":"kmh"},{"json_units":"kmh","targets":[{"angle":35.3773,"distance":13.1895,"id":1294522,"speed":-0.55,"strength":990529}],"timestamp":16620,"ui_units":"kmh"},{"json_units":"kmh","targets":[{"angle":36.7398,"distance":13.0983,"id":1294522,"speed":-0.55,"strength":990529}],"timestamp":16620,"ui_units":"kmh"},{"json_units":"kmh","targets":[{"angle":39.5186,"distance":12.9384,"id":1294522,"speed":-0.55,"strength":990529}],"timestamp":16620,"ui_units":"kmh"},{"json_units":"kmh","targets":[{"angle":40.9322,"distance":12.87,"id":1294522,"speed":-0.55,"strength":990529}],"timestamp":16620,"ui_units":"kmh"},{"json_units":"kmh","targets":[{"angle":42.3601,"distance":12.8096,"id":1294522,"speed":-0.55,"strength":990529}],"timestamp":16621,"ui_units":"kmh"},{"json_units":"kmh","targets":[{"angle":45.2519,"distance":12.713,"id":1294522,"speed":-0.55,"strength":990529}],"timestamp":16621,"ui_units":"kmh"},{"json_units":"kmh","targets":[],"timestamp":16621,"ui_units":"kmh"},{"json_units":"kmh","targets":[],"timestamp":16621,"ui_units":"kmh"},{"json_units":"kmh","targets":[],"timestamp":16622,"ui_units":"kmh"},{"json_units":"kmh","targets":[],"timestamp":16622,"ui_units":"kmh"},{"json_units":"kmh","targets":[],"timestamp":16622,"ui_units":"kmh"},{"json_units":"kmh","targets":[],"timestamp":16622,"ui_units":"kmh"},{"json_units":"kmh","targets":[],"timestamp":16623,"ui_units":"kmh"},{"json_units":"kmh","targets":[],"timestamp":16623,"ui_units":"kmh"},{"json_units":"kmh","targets":[],"timestamp":16623,"ui_units":"kmh"},{"json_units":"kmh","targets":[],"timestamp":16623,"ui_units":"kmh"},{"json_units":"kmh","targets":[],"timestamp":16624,"ui_units":"kmh"},{"json_units":"kmh","targets":[],"timestamp":16624,"ui_units":"kmh"},{"json_units":"kmh","targets":[],"timestamp":16624,"ui_units":"kmh"},{"json_units":"kmh","targets":[],"timestamp":16624,"ui_units":"kmh"},{"json_units":"kmh","targets":[],"timestamp":16625,"ui_units":"kmh"},{"json_units":"kmh","targets":[],"timestamp":16625,"ui_units":"kmh"},{"json_units":"kmh","targets":[],"timestamp":16625,"ui_units":"kmh"}]

